autora/experimentalist/prediction_filter/__init__.py
autora_experimentalist_prediction_filter-1.1.0.dist-info/LICENSE
autora_experimentalist_prediction_filter-1.1.0.dist-info/METADATA
autora_experimentalist_prediction_filter-1.1.0.dist-info/WHEEL
autora_experimentalist_prediction_filter-1.1.0.dist-info/top_level.txt
autora_experimentalist_prediction_filter-1.1.0.dist-info/RECORD
