Metadata-Version: 2.1
Name: autora-experimentalist-prediction-filter
Version: 1.1.0
Summary: Filters condition based on model predictions.
Author-email: Younes Strittmatter <younes_strittmatter@brown.edu>
License: Copyright (c) 2024 Younes Strittmatter
Project-URL: homepage, http://www.empiricalresearch.ai
Project-URL: repository, https://github.com/AutoResearch/autora-experimentalist-prediction-filter
Project-URL: documentation, https://autoresearch.github.io/autora/
Requires-Python: <4,>=3.8
License-File: LICENSE
Requires-Dist: autora-core
Requires-Dist: scikit-learn
Provides-Extra: dev
Requires-Dist: autora-core[dev] ; extra == 'dev'
